anonymizedf/__init__.py
anonymizedf/_version.py
anonymizedf/anonymizedf.py
anonymizedf-1.0.1.dist-info/LICENSE
anonymizedf-1.0.1.dist-info/METADATA
anonymizedf-1.0.1.dist-info/WHEEL
anonymizedf-1.0.1.dist-info/top_level.txt
anonymizedf-1.0.1.dist-info/RECORD
