Metadata-Version: 2.1
Name: anonymizedf
Version: 1.0.1
Summary: a convenient way to anonymize your data for analytics
Home-page: https://github.com/AlexFrid/anonymizedf
Author: Alexander Fridriksson
Author-email: post@alexanderfridriksson.com
License: BSD
Keywords: faker pandas anonymize fake mock data
Platform: UNKNOWN
Classifier: License :: OSI Approved :: BSD License
Classifier: Programming Language :: Python :: 3
Classifier: Programming Language :: Python :: 3.7
Classifier: Development Status :: 5 - Production/Stable
Classifier: Intended Audience :: Developers
Classifier: Topic :: Software Development :: Libraries :: Python Modules
Classifier: Topic :: Scientific/Engineering
Requires-Dist: pandas
Requires-Dist: faker
